pyCalcErr/EquationHandler.py
pyCalcErr/GaussPropagation.py
pyCalcErr/ParseCmdArgs.py
pyCalcErr/__init__.py
pyCalcErr/pyCalcErr.py
pyCalcErr-0.4.1.dist-info/LICENSE
pyCalcErr-0.4.1.dist-info/METADATA
pyCalcErr-0.4.1.dist-info/WHEEL
pyCalcErr-0.4.1.dist-info/entry_points.txt
pyCalcErr-0.4.1.dist-info/top_level.txt
pyCalcErr-0.4.1.dist-info/RECORD
