Metadata-Version: 2.1
Name: pyCalcErr
Version: 0.4.1
Summary: Gauss error propagation with latex formula
Home-page: https://github.com/chcltchunk/pyCalcErr
Author: Jonas Oldenstaedt
License: UNKNOWN
Platform: UNKNOWN
Classifier: Programming Language :: Python :: 3
Classifier: License :: OSI Approved :: MIT License
Classifier: Operating System :: OS Independent
Requires-Python: >=3
Requires-Dist: pytexit
Requires-Dist: sympy
